{
    "home_banner": [ {
        "title": "Welcome back!",
        "titleTextColor": "#FFFFFF",
        "buttonName": "",
        "buttonTextColor": "#FFFFFF",
        "buttonBgColor": "#000000",
        "imageUrl": "https://raw.githubusercontent.com/ultimatronapps/AnimeTV_WebsiteResource/main/SS.png",
	"actionUrl": "",
	"domainName": "",
	"homepage": "",
	"thumbnail": "",
	"isExternal": false,
        "order": 0
    }, {
        "title": "Tokyo Revengers: Tenjiku-hen",
        "titleTextColor": "#FFFFFF",
        "buttonName": "Watch Now",
        "buttonTextColor": "#191919",
        "buttonBgColor": "#4daefe",
        "imageUrl": "https://raw.githubusercontent.com/ultimatronapps/AnimeTV_WebsiteResource/main/TR%20Tenjiku.jpg",
	"actionUrl": "https://aniwatch.to/tokyo-revengers-tenjiku-hen-18575",
	"domainName": "Zoro/AniWatch",
	"homepage": "https://aniwatch.to/home",
	"thumbnail": "https://raw.githubusercontent.com/ultimatronapps/AnimeTV_WebsiteResource/main/thumbnail/AniWatch%20Logo.png",
	"isExternal": false,
        "order": 1
    }, {
        "title": "Spy x Family Season 2",
        "titleTextColor": "#FFFFFF",
        "buttonName": "Watch Now",
        "buttonTextColor": "#191919",
        "buttonBgColor": "#4daefe",
        "imageUrl": "https://raw.githubusercontent.com/ultimatronapps/AnimeTV_WebsiteResource/main/Spy%20X%20Family%202.jpg",
	"actionUrl": "https://aniwatch.to/spy-x-family-season-2-18572",
	"homepage": "https://aniwatch.to/home",
	"thumbnail": "https://raw.githubusercontent.com/ultimatronapps/AnimeTV_WebsiteResource/main/thumbnail/AniWatch%20Logo.png",
	"isExternal": false,
        "order": 2
    }, {
       "title": "Goblin Slayer 2nd Season",
        "titleTextColor": "#FFFFFF",
        "buttonName": "Watch Now",
        "buttonTextColor": "#191919",
        "buttonBgColor": "#4daefe",
       "imageUrl": "https://raw.githubusercontent.com/ultimatronapps/AnimeTV_WebsiteResource/main/Goblin%20Slayer%202.jpg",
	"actionUrl": "https://aniwatch.to/goblin-slayer-2nd-season-17505",
	"domainName": "Zoro/AniWatch",
	"homepage": "https://aniwatch.to/home",
	"thumbnail": "https://raw.githubusercontent.com/ultimatronapps/AnimeTV_WebsiteResource/main/thumbnail/AniWatch%20Logo.png",
	"isExternal": false,
        "order": 3
    }, {
        "title": "The Rising of the Shield Hero Season 3",
        "titleTextColor": "#FFFFFF",
        "buttonName": "Watch Now",
        "buttonTextColor": "#191919",
        "buttonBgColor": "#4daefe",
        "imageUrl": "https://raw.githubusercontent.com/ultimatronapps/AnimeTV_WebsiteResource/main/Sheild%20Hero%20S3.jpeg",
	"actionUrl": "https://aniwatch.to/the-rising-of-the-shield-hero-season-3-15571?ref=search",
	"domainName": "Zoro/AniWatch",
	"homepage": "https://aniwatch.to/home",
	"thumbnail": "https://raw.githubusercontent.com/ultimatronapps/AnimeTV_WebsiteResource/main/thumbnail/AniWatch%20Logo.png",
	"isExternal": false,
        "order": 4
    }]
}
